pytest_depends_on/__init__.py
pytest_depends_on/depends_on.py
pytest_depends_on/consts/__init__.py
pytest_depends_on/consts/status.py
pytest_depends_on-1.0.0.dist-info/licenses/LICENSE
pytest_depends_on-1.0.0.dist-info/METADATA
pytest_depends_on-1.0.0.dist-info/WHEEL
pytest_depends_on-1.0.0.dist-info/entry_points.txt
pytest_depends_on-1.0.0.dist-info/top_level.txt
pytest_depends_on-1.0.0.dist-info/RECORD
