Metadata-Version: 2.4
Name: pytest-depends-on
Version: 1.0.0
Summary: A Python package for managing test dependencies in pytest.
Author: Avi Zaguri
License: MIT
Project-URL: Homepage, https://github.com/aviz92/pytest-depends-on
Project-URL: Repository, https://github.com/aviz92/pytest-depends-on
Project-URL: Issues, https://github.com/aviz92/pytest-depends-on/issues
Keywords: development,python,pytest,pytest-dependensies,dependensies,testing,automation
Classifier: Development Status :: 5 - Production/Stable
Classifier: Intended Audience :: Developers
Classifier: Framework :: Pytest
Classifier: Programming Language :: Python :: 3.11
Requires-Python: >=3.11
License-File: LICENSE
Requires-Dist: build>=1.3.0
Requires-Dist: colorlog>=6.10.1
Requires-Dist: custom-python-logger>=2.0.10
Requires-Dist: pre-commit>=4.5.0
Requires-Dist: pytest>=9.0.1
Requires-Dist: python-dotenv>=1.2.1
Requires-Dist: setuptools>=80.9.0
Requires-Dist: twine>=6.2.0
Requires-Dist: wheel>=0.45.1
Dynamic: license-file
